uwsgi_tools/__init__.py
uwsgi_tools/compat.py
uwsgi_tools/curl.py
uwsgi_tools/proxy.py
uwsgi_tools/utils.py
uwsgi_tools-1.1.1.dist-info/DESCRIPTION.rst
uwsgi_tools-1.1.1.dist-info/METADATA
uwsgi_tools-1.1.1.dist-info/RECORD
uwsgi_tools-1.1.1.dist-info/WHEEL
uwsgi_tools-1.1.1.dist-info/entry_points.txt
uwsgi_tools-1.1.1.dist-info/metadata.json
uwsgi_tools-1.1.1.dist-info/top_level.txt
